DataWattch/__init__.py
DataWattch/domoticz_communication.py
DataWattch/stm_communication.py
DataWattch/Devices/__init__.py
DataWattch/Devices/devices.py
DataWattch-0.2.8.8.dist-info/LICENSE.txt
DataWattch-0.2.8.8.dist-info/METADATA
DataWattch-0.2.8.8.dist-info/WHEEL
DataWattch-0.2.8.8.dist-info/top_level.txt
DataWattch-0.2.8.8.dist-info/RECORD
